<vector xmlns:android="http://schemas.android.com/apk/res/android"
    android:width="200dp"
    android:height="200dp"
    android:viewportWidth="1024"
    android:viewportHeight="1024">
  <path
      android:pathData="M326,233Q283,237 312,260Q369,290 428,277Q543,259 665,239Q720,229 729,222Q739,212 735,202Q728,189 693,178Q660,169 561,199Q420,227 326,233Z"
      android:fillColor="#d3d3d3"/>
  <path
      android:pathData="M329,479Q304,483 332,508Q348,521 385,517Q557,495 685,484Q721,480 709,460Q694,438 657,428Q621,421 558,434Q435,459 329,479Z"
      android:fillColor="#d3d3d3"/>
  <path
      android:pathData="M130,735Q102,738 122,761Q140,780 163,787Q191,796 212,790Q515,721 929,743Q930,742 933,743Q960,744 967,733Q974,717 953,699Q884,645 835,654Q643,690 130,735Z"
      android:fillColor="#d3d3d3"/>
  <group>
    <clip-path android:pathData="M326,233Q283,237 312,260Q369,290 428,277Q543,259 665,239Q720,229 729,222Q739,212 735,202Q728,189 693,178Q660,169 561,199Q420,227 326,233Z M 0,0"/>
    <path
        android:pathData="M316,245L367,255L416,252L660,208L722,208"
        android:name="stroke_1"
        android:strokeLineJoin="round"
        android:strokeWidth="160"
        android:strokeColor="@color/color_HSK_primary"
        android:strokeLineCap="round"
        android:trimPathEnd="0"/>
  </group>
  <group>
    <clip-path android:pathData="M329,479Q304,483 332,508Q348,521 385,517Q557,495 685,484Q721,480 709,460Q694,438 657,428Q621,421 558,434Q435,459 329,479Z M 0,0"/>
    <path
        android:pathData="M331,493L375,495L628,457L657,457L700,468"
        android:name="stroke_2"
        android:strokeLineJoin="round"
        android:strokeWidth="160"
        android:strokeColor="@color/color_HSK_primary"
        android:strokeLineCap="round"
        android:trimPathEnd="0"/>
  </group>
  <group>
    <clip-path android:pathData="M130,735Q102,738 122,761Q140,780 163,787Q191,796 212,790Q515,721 929,743Q930,742 933,743Q960,744 967,733Q974,717 953,699Q884,645 835,654Q643,690 130,735Z M 0,0"/>
    <path
        android:pathData="M127,748L158,758L195,761L500,722L846,696L881,700L955,726"
        android:name="stroke_3"
        android:strokeLineJoin="round"
        android:strokeWidth="160"
        android:strokeColor="@color/color_HSK_primary"
        android:strokeLineCap="round"
        android:trimPathEnd="0"/>
  </group>
</vector>
